zotnote/__init__.py
zotnote/__main__.py
zotnote/__version__.py
zotnote/app.py
zotnote/cli.py
zotnote/config/config.py
zotnote/config/config.toml.example
zotnote/connectors/bbt.py
zotnote/notes/note.py
zotnote/notes/templates/content/empirical.j2
zotnote/notes/templates/content/simple.j2
zotnote/notes/templates/master.j2
zotnote/utils/helpers.py
zotnote-0.3.5.dist-info/entry_points.txt
zotnote-0.3.5.dist-info/LICENSE
zotnote-0.3.5.dist-info/WHEEL
zotnote-0.3.5.dist-info/METADATA
zotnote-0.3.5.dist-info/RECORD
