Metadata-Version: 2.1
Name: zotnote
Version: 0.3.5
Summary: Streamlining reading notes with Zotero
Home-page: https://github.com/bubblbu/zotnote
License: MIT
Keywords: zotero,literature-review,reading-notes
Author: Asura Enkhbayar
Author-email: asura.enkhbayar@gmail.com
Requires-Python: >=3.6,<4.0
Classifier: License :: OSI Approved :: MIT License
Classifier: Programming Language :: Python :: 3
Classifier: Programming Language :: Python :: 3.6
Classifier: Programming Language :: Python :: 3.7
Classifier: Programming Language :: Python :: 3.8
Requires-Dist: click (>=7.1.1,<8.0.0)
Requires-Dist: click-option-group (>=0.3.0,<0.4.0)
Requires-Dist: jinja2 (>=2.11.1,<3.0.0)
Requires-Dist: requests (>=2.23.0,<3.0.0)
Requires-Dist: tomlkit (>=0.5.11,<0.6.0)
Requires-Dist: xdg (>=4.0.1,<5.0.0)
Project-URL: Repository, https://github.com/bubblbu/zotnote
